pyelectric/__init__.py
pyelectric/ac/__init__.py
pyelectric/ac/phasor/__init__.py
pyelectric/ac/phasor/plot.py
pyelectric/ac/power/__init__.py
pyelectric/ac/power/correct_power_factor.py
pyelectric/ac/power/plot.py
pyelectric/electronic/__init__.py
pyelectric/electronic/amplifier/__init__.py
pyelectric/electronic/amplifier/drawing.py
pyelectric/electronic/amplifier/input.py
pyelectric/electronic/amplifier/output.py
pyelectric/electronic/amplifier/common_base_polarization_tbj/__init__.py
pyelectric/electronic/amplifier/common_base_polarization_tbj/drawing.py
pyelectric/electronic/amplifier/common_base_polarization_tbj/input.py
pyelectric/electronic/amplifier/common_base_polarization_tbj/output.py
pyelectric/electronic/amplifier/common_drain_polarization_fet/__init__.py
pyelectric/electronic/amplifier/common_drain_polarization_fet/drawing.py
pyelectric/electronic/amplifier/common_drain_polarization_fet/input.py
pyelectric/electronic/amplifier/common_drain_polarization_fet/output.py
pyelectric/electronic/amplifier/fixed_polarization_fet/__init__.py
pyelectric/electronic/amplifier/fixed_polarization_fet/drawing.py
pyelectric/electronic/amplifier/fixed_polarization_fet/input.py
pyelectric/electronic/amplifier/fixed_polarization_fet/output.py
pyelectric/electronic/amplifier/fixed_polarization_tbj/__init__.py
pyelectric/electronic/amplifier/fixed_polarization_tbj/drawing.py
pyelectric/electronic/amplifier/fixed_polarization_tbj/input.py
pyelectric/electronic/amplifier/fixed_polarization_tbj/output.py
pyelectric/electronic/amplifier/follower_emitter_polarization_tbj/__init__.py
pyelectric/electronic/amplifier/follower_emitter_polarization_tbj/drawing.py
pyelectric/electronic/amplifier/follower_emitter_polarization_tbj/input.py
pyelectric/electronic/amplifier/follower_emitter_polarization_tbj/output.py
pyelectric/electronic/amplifier/voltage_divider_polarization_fet/__init__.py
pyelectric/electronic/amplifier/voltage_divider_polarization_fet/drawing.py
pyelectric-0.5.4.dist-info/LICENSE
pyelectric-0.5.4.dist-info/METADATA
pyelectric-0.5.4.dist-info/WHEEL
pyelectric-0.5.4.dist-info/top_level.txt
pyelectric-0.5.4.dist-info/RECORD
