Metadata-Version: 2.1
Name: pyelectric
Version: 0.5.4
Summary: Python package for electric circuits
Home-page: https://github.com/luanws/pyelectric
Author: luanws
Author-email: luan.w.silveira@gmail.com
License: UNKNOWN
Platform: UNKNOWN
Classifier: Programming Language :: Python :: 3
Classifier: License :: OSI Approved :: MIT License
Classifier: Operating System :: OS Independent
Requires-Python: >=3.7
Requires-Dist: numpy
Requires-Dist: matplotlib
